{
  "as_of": "2025-08-08",
  "risk": 0.42,
  "band": "yellow",
  "regime": "liquidity_on",
  "btc_price_usd": 116502.77,
  "etf_flow_usd": 655300000.0,
  "etf_flow_sma7_usd": 168057142.86,
  "drivers": {
    "etf_flows": {
      "score": 0.3,
      "contribution": -0.04,
      "raw_usd": 655300000.0,
      "sma7_usd": 168057142.86,
      "asof": "11 Jan 2024",
      "trailing": [
        {
          "date": "11 Jan 2024",
          "usd": 655300000.0
        },
        {
          "date": "12 Jan 2024",
          "usd": 203000000.0
        },
        {
          "date": "15 Jan 2024",
          "usd": 0.0
        },
        {
          "date": "16 Jan 2024",
          "usd": -52700000.0
        },
        {
          "date": "17 Jan 2024",
          "usd": 453800000.0
        },
        {
          "date": "18 Jan 2024",
          "usd": -126600000.0
        },
        {
          "date": "19 Jan 2024",
          "usd": 43600000.0
        }
      ],
      "source": "Farside 'Bitcoin ETF Flow \u2013 All Data'"
    },
    "net_liquidity": {
      "score": 0.44,
      "contribution": 0.08,
      "raw": null
    },
    "stablecoins": {
      "score": 0.39,
      "contribution": 0.08,
      "raw": null
    },
    "term_structure": {
      "score": 0.21,
      "contribution": 0.12,
      "raw_basis_pct": null
    },
    "onchain": {
      "score": 0.65,
      "contribution": 0.08,
      "raw": null
    }
  }
}