{
  "as_of": "2026-03-06",
  "as_of_utc": "2026-03-06T13:09:35Z",
  "smooth_days": 21,
  "risk": 0.47,
  "band": "yellow",
  "regime": "liquidity_on",
  "btc_price_usd": 69949.21,
  "etf_flow_usd": 655300000.0,
  "etf_flow_sma7_usd": 106228571.43,
  "stablecoin_delta_usd": -5544469.18,
  "stablecoin_delta_sma7_usd": 190835658.64,
  "drivers": {
    "etf_flows": {
      "score": 0.37,
      "contribution": -0.03,
      "raw_usd": 655300000.0,
      "sma7_usd": 106228571.43,
      "asof": "11 Jan 2024",
      "trailing": [
        {
          "date": "11 Jan 2024",
          "usd": 655300000.0
        },
        {
          "date": "12 Jan 2024",
          "usd": 203000000.0
        },
        {
          "date": "15 Jan 2024",
          "usd": 0.0
        },
        {
          "date": "16 Jan 2024",
          "usd": -52700000.0
        },
        {
          "date": "17 Jan 2024",
          "usd": 453800000.0
        },
        {
          "date": "18 Jan 2024",
          "usd": -126600000.0
        },
        {
          "date": "19 Jan 2024",
          "usd": 43600000.0
        },
        {
          "date": "22 Jan 2024",
          "usd": -87400000.0
        },
        {
          "date": "23 Jan 2024",
          "usd": -106100000.0
        },
        {
          "date": "24 Jan 2024",
          "usd": -158300000.0
        },
        {
          "date": "25 Jan 2024",
          "usd": -79800000.0
        },
        {
          "date": "26 Jan 2024",
          "usd": 14800000.0
        },
        {
          "date": "29 Jan 2024",
          "usd": 255100000.0
        },
        {
          "date": "30 Jan 2024",
          "usd": 247300000.0
        },
        {
          "date": "31 Jan 2024",
          "usd": 197600000.0
        },
        {
          "date": "01 Feb 2024",
          "usd": 38500000.0
        },
        {
          "date": "02 Feb 2024",
          "usd": 80000000.0
        },
        {
          "date": "05 Feb 2024",
          "usd": 68100000.0
        },
        {
          "date": "06 Feb 2024",
          "usd": 33600000.0
        },
        {
          "date": "07 Feb 2024",
          "usd": 146000000.0
        },
        {
          "date": "08 Feb 2024",
          "usd": 405000000.0
        }
      ],
      "source": "Farside Bitcoin ETF Flow \u2013 All Data",
      "asof_utc": "2024-01-11T00:00:00Z",
      "health": {
        "status": "stale",
        "age_hours": 18853.2
      }
    },
    "net_liquidity": {
      "score": 0.49,
      "contribution": -0.0,
      "level_usd": 5794048000000.0,
      "delta1d_usd": 0.0,
      "sma7_delta_usd": 4159476190.48,
      "trailing": [
        {
          "date": "06 Mar 2026",
          "usd": 0.0
        },
        {
          "date": "05 Mar 2026",
          "usd": -1916000000.0
        },
        {
          "date": "04 Mar 2026",
          "usd": 70982000000.0
        },
        {
          "date": "03 Mar 2026",
          "usd": -576000000.0
        },
        {
          "date": "02 Mar 2026",
          "usd": 15691000000.0
        },
        {
          "date": "01 Mar 2026",
          "usd": 0.0
        },
        {
          "date": "28 Feb 2026",
          "usd": 0.0
        }
      ],
      "asof": "06 Mar 2026",
      "asof_utc": "2026-03-06T00:00:00Z",
      "source": "FRED WALCL \u2212 WTREGEN \u2212 RRPONTSYD (USD)",
      "health": {
        "status": "ok",
        "age_hours": 13.2
      }
    },
    "stablecoins": {
      "score": 0.45,
      "contribution": -0.01,
      "raw_delta_usd": -5544469.18,
      "sma7_delta_usd": 190835658.64,
      "trailing": [
        {
          "date": "06 Mar 2026",
          "usd": -5544469.18
        },
        {
          "date": "06 Mar 2026",
          "usd": 412897897.79
        },
        {
          "date": "05 Mar 2026",
          "usd": 734760328.93
        },
        {
          "date": "04 Mar 2026",
          "usd": 491941636.18
        },
        {
          "date": "03 Mar 2026",
          "usd": 738174186.57
        },
        {
          "date": "02 Mar 2026",
          "usd": 6170158.08
        },
        {
          "date": "01 Mar 2026",
          "usd": 55837349.68
        },
        {
          "date": "28 Feb 2026",
          "usd": -83333878.9
        },
        {
          "date": "27 Feb 2026",
          "usd": -143951737.96
        },
        {
          "date": "26 Feb 2026",
          "usd": 440750892.32
        },
        {
          "date": "25 Feb 2026",
          "usd": 219086960.88
        },
        {
          "date": "24 Feb 2026",
          "usd": 338134870.03
        },
        {
          "date": "23 Feb 2026",
          "usd": -136823943.62
        },
        {
          "date": "22 Feb 2026",
          "usd": 34730426.71
        },
        {
          "date": "21 Feb 2026",
          "usd": 587326901.29
        },
        {
          "date": "20 Feb 2026",
          "usd": 255331730.34
        },
        {
          "date": "19 Feb 2026",
          "usd": 80507286.68
        },
        {
          "date": "18 Feb 2026",
          "usd": -179464575.25
        },
        {
          "date": "17 Feb 2026",
          "usd": 52811281.15
        },
        {
          "date": "16 Feb 2026",
          "usd": 13700136.93
        },
        {
          "date": "15 Feb 2026",
          "usd": 94505392.85
        }
      ],
      "source": "CoinGecko USDT + USDC market_caps (daily)",
      "asof": "06 Mar 2026",
      "asof_utc": "2026-03-06T00:00:00Z",
      "health": {
        "status": "ok",
        "age_hours": 13.2
      }
    },
    "term_structure": {
      "score": 0.42,
      "contribution": -0.02,
      "funding_ann_pct": 2.47,
      "funding_8h_pct": 0.0023,
      "perp_premium_now_pct": 0.008,
      "perp_premium_7d_pct": 0.008,
      "source": "Binance/OKX/BitMEX/Bybit/Deribit/Proxy",
      "asof_utc": "2026-03-06T13:09:35Z",
      "health": {
        "status": "ok",
        "age_hours": 0.0
      }
    },
    "onchain": {
      "score": 0.52,
      "contribution": 0.0,
      "addr_today": 522467.0,
      "addr_avg_w": 480472.0,
      "tx_today": 464513.0,
      "tx_avg_w": 483246.0,
      "fee_usd_today": 192654.39,
      "fee_usd_avg_w": 178169.89,
      "hash_mom_pct": 2.23,
      "mempool_vsize_mb": 25.79,
      "mempool_halfhour_satvb": 1.0,
      "trailing": [
        {
          "date": "05 Mar 2026",
          "usd": 192654.39
        },
        {
          "date": "04 Mar 2026",
          "usd": 211990.98
        },
        {
          "date": "03 Mar 2026",
          "usd": 189215.41
        },
        {
          "date": "02 Mar 2026",
          "usd": 185981.41
        },
        {
          "date": "01 Mar 2026",
          "usd": 178566.38
        },
        {
          "date": "28 Feb 2026",
          "usd": 176799.22
        },
        {
          "date": "27 Feb 2026",
          "usd": 210937.74
        },
        {
          "date": "26 Feb 2026",
          "usd": 239986.06
        },
        {
          "date": "25 Feb 2026",
          "usd": 203862.86
        },
        {
          "date": "24 Feb 2026",
          "usd": 188555.4
        },
        {
          "date": "23 Feb 2026",
          "usd": 182209.79
        },
        {
          "date": "22 Feb 2026",
          "usd": 131441.64
        },
        {
          "date": "21 Feb 2026",
          "usd": 151065.49
        },
        {
          "date": "20 Feb 2026",
          "usd": 181219.71
        },
        {
          "date": "19 Feb 2026",
          "usd": 164930.78
        },
        {
          "date": "18 Feb 2026",
          "usd": 161329.72
        },
        {
          "date": "17 Feb 2026",
          "usd": 160200.47
        },
        {
          "date": "16 Feb 2026",
          "usd": 155029.59
        },
        {
          "date": "15 Feb 2026",
          "usd": 129506.98
        },
        {
          "date": "14 Feb 2026",
          "usd": 152708.24
        },
        {
          "date": "13 Feb 2026",
          "usd": 193375.39
        }
      ],
      "source": "blockchain.com (addr/tx/fees/hash) + mempool.space",
      "asof_utc": "2026-03-06T13:09:35Z",
      "health": {
        "status": "ok",
        "age_hours": 0.0
      }
    }
  }
}